_shellinford.cp38-win32.pyd
shellinford/__init__.py
shellinford/shellinford.py
shellinford-0.4.1.data/headers/shellinford_bit_vector.h
shellinford-0.4.1.data/headers/shellinford_fm_index.h
shellinford-0.4.1.data/headers/shellinford_succinct_vector.h
shellinford-0.4.1.data/headers/shellinford_wavelet_matrix.h
shellinford-0.4.1.data/headers/shellinford_wavelet_tree.h
shellinford-0.4.1.dist-info/LICENSE
shellinford-0.4.1.dist-info/METADATA
shellinford-0.4.1.dist-info/WHEEL
shellinford-0.4.1.dist-info/top_level.txt
shellinford-0.4.1.dist-info/RECORD
