Metadata-Version: 2.1
Name: shellinford
Version: 0.4.1
Summary: Wavelet Matrix/Tree succinct data structure for full text search (using shellinford C++ library)
Home-page: https://github.com/ikegami-yukino/shellinford-python
Author: Yukino Ikegami
Author-email: yknikgm@gmail.com
License: UNKNOWN
Keywords: full text search,FM-index,Wavelet Matrix
Platform: UNKNOWN
Classifier: Development Status :: 3 - Alpha
Classifier: Intended Audience :: Developers
Classifier: Intended Audience :: Science/Research
Classifier: License :: OSI Approved :: BSD License
Classifier: Programming Language :: C++
Classifier: Programming Language :: Python :: 2.7
Classifier: Programming Language :: Python :: 3.3
Classifier: Programming Language :: Python :: 3.4
Classifier: Programming Language :: Python :: 3.5
Classifier: Programming Language :: Python :: 3.6
Classifier: Programming Language :: Python :: 3.7
Classifier: Topic :: Software Development :: Libraries :: Python Modules
Classifier: Topic :: Scientific/Engineering :: Information Analysis
Classifier: Topic :: Text Processing :: Linguistic
Classifier: Topic :: Text Processing :: Indexing
